setup.py
iai/Axis.py
iai/Controller.py
iai/DigitalIO.py
iai/Space.py
iai/__init__.py
iai/__main__.py
iai/utilities.py
pyiai.egg-info/PKG-INFO
pyiai.egg-info/SOURCES.txt
pyiai.egg-info/dependency_links.txt
pyiai.egg-info/requires.txt
pyiai.egg-info/top_level.txt
tests/__init__.py
tests/test_axis.py
tests/test_controller.py
tests/test_digital_io.py
tests/test_space.py
tests/test_utilities.py