Metadata-Version: 1.1
Name: pyiai
Version: 0.0.2
Summary: A library for the iai robot controller.
Home-page: UNKNOWN
Author: Boddmg
Author-email: boddmg@gmail.com
License: MIT
Keywords: iai robot controller
Platform: UNKNOWN
Classifier: Development Status :: 3 - Alpha
Classifier: Intended Audience :: Developers
Classifier: Topic :: Software Development :: Build Tools
Classifier: License :: OSI Approved :: MIT License
Classifier: Programming Language :: Python :: 2.7
Classifier: Programming Language :: Python :: 3
Classifier: Programming Language :: Python :: 3.2
Classifier: Programming Language :: Python :: 3.3
Classifier: Programming Language :: Python :: 3.4
